pygamegui/__init__.py
pygamegui/gui/AnimatedView.py
pygamegui/gui/Button.py
pygamegui/gui/DialogView.py
pygamegui/gui/ImageView.py
pygamegui/gui/LinearGradient.py
pygamegui/gui/LinearLayout.py
pygamegui/gui/Manager.py
pygamegui/gui/ScrollView.py
pygamegui/gui/TextView.py
pygamegui/gui/View.py
pygamegui/gui/__init__.py
pygamegui/utils/RoundRect.py
pygamegui/utils/ThreadCreator.py
pygamegui/utils/Timer.py
pygamegui/utils/__init__.py
pygamegui-0.1.2.dist-info/LICENSE
pygamegui-0.1.2.dist-info/METADATA
pygamegui-0.1.2.dist-info/WHEEL
pygamegui-0.1.2.dist-info/top_level.txt
pygamegui-0.1.2.dist-info/RECORD
